packet_parser_top.v
`timescale 1ns / 1ps

module packet_parser_top (
    input  wire        clk,
    input  wire        rst_n,

    // AXI4-Stream Input Interface
    input  wire [7:0]  s_axis_tdata,
    input  wire        s_axis_tvalid,
    input  wire        s_axis_tlast,
    output wire        s_axis_tready,

    // Parsed Field Registers
    output reg [31:0]  parsed_src_ip,
    output reg [31:0]  parsed_dst_ip,
    output reg [15:0]  parsed_src_port,
    output reg [15:0]  parsed_dst_port,
    output reg         payload_valid
);

    // Accept incoming bytes on every clock cycle
    assign s_axis_tready = 1'b1;

    // FSM States
    localparam STATE_ETH     = 3'd0;
    localparam STATE_IPV4    = 3'd1;
    localparam STATE_TCP     = 3'd2;
    localparam STATE_PAYLOAD = 3'd3;

    reg [2:0] state;
    reg [7:0] byte_cnt;

    always @(posedge clk or negedge rst_n) begin
        if (!rst_n) begin
            state           <= STATE_ETH;
            byte_cnt        <= 8'd0;
            parsed_src_ip   <= 32'd0;
            parsed_dst_ip   <= 32'd0;
            parsed_src_port <= 16'd0;
            parsed_dst_port <= 16'd0;
            payload_valid   <= 1'b0;
        end else if (s_axis_tvalid) begin
            // Reset state machine on packet termination
            if (s_axis_tlast) begin
                state         <= STATE_ETH;
                byte_cnt      <= 8'd0;
                payload_valid <= 1'b0;
            end else begin
                case (state)
                    // Ethernet Header (14 bytes)
                    STATE_ETH: begin
                        if (byte_cnt == 8'd13) begin
                            state    <= STATE_IPV4;
                            byte_cnt <= 8'd0;
                        end else begin
                            byte_cnt <= byte_cnt + 1'b1;
                        end
                    end

                    // IPv4 Header (20 bytes standard)
                    STATE_IPV4: begin
                        case (byte_cnt)
                            8'd12, 8'd13, 8'd14, 8'd15: parsed_src_ip <= {parsed_src_ip[23:0], s_axis_tdata};
                            8'd16, 8'd17, 8'd18, 8'd19: parsed_dst_ip <= {parsed_dst_ip[23:0], s_axis_tdata};
                        endcase

                        if (byte_cnt == 8'd19) begin
                            state    <= STATE_TCP;
                            byte_cnt <= 8'd0;
                        end else begin
                            byte_cnt <= byte_cnt + 1'b1;
                        end
                    end

                    // TCP Header (20 bytes standard)
                    STATE_TCP: begin
                        case (byte_cnt)
                            8'd0, 8'd1: parsed_src_port <= {parsed_src_port[7:0], s_axis_tdata};
                            8'd2, 8'd3: parsed_dst_port <= {parsed_dst_port[7:0], s_axis_tdata};
                        endcase

                        if (byte_cnt == 8'd19) begin
                            state         <= STATE_PAYLOAD;
                            payload_valid <= 1'b1;
                        end else begin
                            byte_cnt <= byte_cnt + 1'b1;
                        end
                    end

                    // Payload Region (Streaming to DPI engine)
                    STATE_PAYLOAD: begin
                        payload_valid <= 1'b1;
                    end

                    default: state <= STATE_ETH;
                endcase
            end
        end
    end

endmodule

tb_parser.v
`timescale 1ns / 1ps

module tb_parser();
    reg clk;
    reg rst_n;
    reg [7:0] s_axis_tdata;
    reg s_axis_tvalid;
    reg s_axis_tlast;
    wire s_axis_tready;

    wire [31:0] src_ip, dst_ip;
    wire [15:0] src_port, dst_port;
    wire payload_valid;

    // Unit Under Test (UUT)
    packet_parser_top uut (
        .clk(clk),
        .rst_n(rst_n),
        .s_axis_tdata(s_axis_tdata),
        .s_axis_tvalid(s_axis_tvalid),
        .s_axis_tlast(s_axis_tlast),
        .s_axis_tready(s_axis_tready),
        .parsed_src_ip(src_ip),
        .parsed_dst_ip(dst_ip),
        .parsed_src_port(src_port),
        .parsed_dst_port(dst_port),
        .payload_valid(payload_valid)
    );

    // 100MHz Clock Generation
    always #5 clk = ~clk;

    // Frame storage: 14B Eth + 20B IPv4 + 20B TCP + 7B Payload
    reg [7:0] mock_packet [0:60];
    integer i;

    initial begin
        // Ethernet Header: EtherType = 0x0800 (IPv4)
        mock_packet[12] = 8'h08; mock_packet[13] = 8'h00; 

        // IPv4 Header:
        // Src IP: 192.168.2.10 -> 0xC0, 0xA8, 0x02, 0x0A
        mock_packet[14+12] = 8'hC0; mock_packet[14+13] = 8'hA8; 
        mock_packet[14+14] = 8'h02; mock_packet[14+15] = 8'h0A;

        // Dst IP: 192.168.2.1  -> 0xC0, 0xA8, 0x02, 0x01
        mock_packet[14+16] = 8'hC0; mock_packet[14+17] = 8'hA8; 
        mock_packet[14+18] = 8'h02; mock_packet[14+19] = 8'h01;

        // TCP Header:
        // Src Port: 12345 -> 0x3039
        mock_packet[34+0] = 8'h30; mock_packet[34+1] = 8'h39;
        // Dst Port: 80    -> 0x0050
        mock_packet[34+2] = 8'h00; mock_packet[34+3] = 8'h50;

        // Payload: "MALWARE"
        mock_packet[54] = "M"; mock_packet[55] = "A";
        mock_packet[56] = "L"; mock_packet[57] = "W";
        mock_packet[58] = "A"; mock_packet[59] = "R";
        mock_packet[60] = "E";

        // Initial Signal States
        clk = 0;
        rst_n = 0;
        s_axis_tvalid = 0;
        s_axis_tlast = 0;
        s_axis_tdata = 8'h00;

        // VCD waveform dump
        $dumpfile("parser_wave.vcd");
        $dumpvars(0, tb_parser);

        // Hold reset for 20ns
        #20 rst_n = 1;
        #10;

        // Stream the packet byte-by-byte into the parser
        for (i = 0; i < 61; i = i + 1) begin
            @(posedge clk);
            s_axis_tvalid <= 1'b1;
            s_axis_tdata  <= mock_packet[i];
            s_axis_tlast  <= (i == 60) ? 1'b1 : 1'b0;
        end

        // Deassert AXI Stream
        @(posedge clk);
        s_axis_tvalid <= 1'b0;
        s_axis_tlast  <= 1'b0;
        s_axis_tdata  <= 8'h00;

        #50;
        $display("----------------------------------------");
        $display("PARSER EXTRACTION RESULTS:");
        $display("Source IP      : %h (Expected: c0a8020a)", src_ip);
        $display("Destination IP : %h (Expected: c0a80201)", dst_ip);
        $display("Source Port    : %d (Expected: 12345 / 0x3039)", src_port);
        $display("Destination Port: %d (Expected: 80 / 0x0050)", dst_port);
        $display("Payload Valid  : %b", payload_valid);
        $display("----------------------------------------");
        $finish;
    end
endmodule

parser_wave.vcd
$date
	Wed Sep 02 12:13:13 2026
$end
$version
	Icarus Verilog
$end
$timescale
	1ps
$end
$scope module tb_parser $end
$var wire 1 ! s_axis_tready $end
$var wire 16 " src_port [15:0] $end
$var wire 32 # src_ip [31:0] $end
$var wire 1 $ payload_valid $end
$var wire 16 % dst_port [15:0] $end
$var wire 32 & dst_ip [31:0] $end
$var reg 1 ' clk $end
$var reg 1 ( rst_n $end
$var reg 8 ) s_axis_tdata [7:0] $end
$var reg 1 * s_axis_tlast $end
$var reg 1 + s_axis_tvalid $end
$var integer 32 , i [31:0] $end
$scope module uut $end
$var wire 1 ' clk $end
$var wire 1 ( rst_n $end
$var wire 8 - s_axis_tdata [7:0] $end
$var wire 1 * s_axis_tlast $end
$var wire 1 ! s_axis_tready $end
$var wire 1 + s_axis_tvalid $end
$var parameter 3 . STATE_ETH $end
$var parameter 3 / STATE_IPV4 $end
$var parameter 3 0 STATE_PAYLOAD $end
$var parameter 3 1 STATE_TCP $end
$var reg 8 2 byte_cnt [7:0] $end
$var reg 32 3 parsed_dst_ip [31:0] $end
$var reg 16 4 parsed_dst_port [15:0] $end
$var reg 32 5 parsed_src_ip [31:0] $end
$var reg 16 6 parsed_src_port [15:0] $end
$var reg 1 $ payload_valid $end
$var reg 3 7 state [2:0] $end
$upscope $end
$upscope $end
$enddefinitions $end
$comment Show the parameter values. $end
$dumpall
b10 1
b11 0
b1 /
b0 .
$end
#0
$dumpvars
b0 7
b0 6
b0 5
b0 4
b0 3
b0 2
b0 -
bx ,
0+
0*
b0 )
0(
0'
b0 &
b0 %
0$
b0 #
b0 "
1!
$end
#5000
1'
#10000
0'
#15000
1'
#20000
0'
1(
#25000
1'
#30000
0'
b0 ,
#35000
bx )
bx -
1+
b1 ,
1'
#40000
0'
#45000
b1 2
b10 ,
1'
#50000
0'
#55000
b10 2
b11 ,
1'
#60000
0'
#65000
b11 2
b100 ,
1'
#70000
0'
#75000
b100 2
b101 ,
1'
#80000
0'
#85000
b101 2
b110 ,
1'
#90000
0'
#95000
b110 2
b111 ,
1'
#100000
0'
#105000
b111 2
b1000 ,
1'
#110000
0'
#115000
b1000 2
b1001 ,
1'
#120000
0'
#125000
b1001 2
b1010 ,
1'
#130000
0'
#135000
b1010 2
b1011 ,
1'
#140000
0'
#145000
b1011 2
b1100 ,
1'
#150000
0'
#155000
b1100 2
b1000 )
b1000 -
b1101 ,
1'
#160000
0'
#165000
b1101 2
b0 )
b0 -
b1110 ,
1'
#170000
0'
#175000
b0 2
b1 7
bx )
bx -
b1111 ,
1'
#180000
0'
#185000
b1 2
b10000 ,
1'
#190000
0'
#195000
b10 2
b10001 ,
1'
#200000
0'
#205000
b11 2
b10010 ,
1'
#210000
0'
#215000
b100 2
b10011 ,
1'
#220000
0'
#225000
b101 2
b10100 ,
1'
#230000
0'
#235000
b110 2
b10101 ,
1'
#240000
0'
#245000
b111 2
b10110 ,
1'
#250000
0'
#255000
b1000 2
b10111 ,
1'
#260000
0'
#265000
b1001 2
b11000 ,
1'
#270000
0'
#275000
b1010 2
b11001 ,
1'
#280000
0'
#285000
b1011 2
b11010 ,
1'
#290000
0'
#295000
b1100 2
b11000000 )
b11000000 -
b11011 ,
1'
#300000
0'
#305000
b1101 2
b11000000 #
b11000000 5
b10101000 )
b10101000 -
b11100 ,
1'
#310000
0'
#315000
b1110 2
b1100000010101000 #
b1100000010101000 5
b10 )
b10 -
b11101 ,
1'
#320000
0'
#325000
b1111 2
b110000001010100000000010 #
b110000001010100000000010 5
b1010 )
b1010 -
b11110 ,
1'
#330000
0'
#335000
b10000 2
b11000000101010000000001000001010 #
b11000000101010000000001000001010 5
b11000000 )
b11000000 -
b11111 ,
1'
#340000
0'
#345000
b10001 2
b11000000 &
b11000000 3
b10101000 )
b10101000 -
b100000 ,
1'
#350000
0'
#355000
b10010 2
b1100000010101000 &
b1100000010101000 3
b10 )
b10 -
b100001 ,
1'
#360000
0'
#365000
b10011 2
b110000001010100000000010 &
b110000001010100000000010 3
b1 )
b1 -
b100010 ,
1'
#370000
0'
#375000
b0 2
b10 7
b11000000101010000000001000000001 &
b11000000101010000000001000000001 3
b110000 )
b110000 -
b100011 ,
1'
#380000
0'
#385000
b1 2
b110000 "
b110000 6
b111001 )
b111001 -
b100100 ,
1'
#390000
0'
#395000
b10 2
b11000000111001 "
b11000000111001 6
b0 )
b0 -
b100101 ,
1'
#400000
0'
#405000
b11 2
b1010000 )
b1010000 -
b100110 ,
1'
#410000
0'
#415000
b100 2
b1010000 %
b1010000 4
bx )
bx -
b100111 ,
1'
#420000
0'
#425000
b101 2
b101000 ,
1'
#430000
0'
#435000
b110 2
b101001 ,
1'
#440000
0'
#445000
b111 2
b101010 ,
1'
#450000
0'
#455000
b1000 2
b101011 ,
1'
#460000
0'
#465000
b1001 2
b101100 ,
1'
#470000
0'
#475000
b1010 2
b101101 ,
1'
#480000
0'
#485000
b1011 2
b101110 ,
1'
#490000
0'
#495000
b1100 2
b101111 ,
1'
#500000
0'
#505000
b1101 2
b110000 ,
1'
#510000
0'
#515000
b1110 2
b110001 ,
1'
#520000
0'
#525000
b1111 2
b110010 ,
1'
#530000
0'
#535000
b10000 2
b110011 ,
1'
#540000
0'
#545000
b10001 2
b110100 ,
1'
#550000
0'
#555000
b10010 2
b110101 ,
1'
#560000
0'
#565000
b10011 2
b110110 ,
1'
#570000
0'
#575000
1$
b11 7
b1001101 )
b1001101 -
b110111 ,
1'
#580000
0'
#585000
b1000001 )
b1000001 -
b111000 ,
1'
#590000
0'
#595000
b1001100 )
b1001100 -
b111001 ,
1'
#600000
0'
#605000
b1010111 )
b1010111 -
b111010 ,
1'
#610000
0'
#615000
b1000001 )
b1000001 -
b111011 ,
1'
#620000
0'
#625000
b1010010 )
b1010010 -
b111100 ,
1'
#630000
0'
#635000
1*
b1000101 )
b1000101 -
b111101 ,
1'
#640000
0'
#645000
0$
b0 2
b0 7
b0 )
b0 -
0*
0+
1'
